rioflux/__init__.py
rioflux/models/__init__.py
rioflux/models/dag.py
rioflux/models/status.py
rioflux/operator/__init__.py
rioflux/operator/agent.py
rioflux/operator/base_operator.py
rioflux/operator/python.py
rioflux-0.1.1.dist-info/METADATA
rioflux-0.1.1.dist-info/WHEEL
rioflux-0.1.1.dist-info/licenses/LICENSE
rioflux-0.1.1.dist-info/RECORD
