Metadata-Version: 2.4
Name: rioflux
Version: 0.1.1
Summary: A simple agent flow engine for Python
Author-email: Veinkr Finch <veinkr.finch@gmail.com>
License-File: LICENSE
Requires-Python: >=3.13
Provides-Extra: test
Requires-Dist: pytest-cov>=4.0.0; extra == 'test'
Requires-Dist: pytest>=7.0.0; extra == 'test'
